Workbook

Sheet Rule of 60
A1: Solopreneur scenario planner
A2: The Rule of 60 — tax read directly from the Tax - Canada (2026) sheet (no rate approximation)
A4: Inputs | D4: Output | E4: Monthly | F4: Yearly
A5: Hourly rate ($) | B5: 200 | D5: Weekly revenue | E5: =B5*B6 -> 5000 | F5: =B5*B6 -> 5000
A6: Hours per week | B6: 25 | D6: Monthly revenue | E6: =E5*4 -> 20000 | F6: =F5*4 -> 20000
A7: Weeks paid per year | B7: 48 | D7: Annual revenue | F7: =F5*B7 -> 240000
A8: Health insurance ($ / month) | B8: 1500 | D8: Health insurance | E8: =B8 -> 1500 | F8: =B8*B10 -> 18000
A9: Other expenses ($ / month) | B9: 750 | D9: Expenses | E9: =B9 -> 750 | F9: =B9*B10 -> 9000
A10: Months paid per year | B10: =B7/4 -> 12 | D10: Revenue less ins. & exp. | E10: =E6-E8-E9 -> 17750 | F10: =F7-F8-F9 -> 213000
D11: Federal tax (from tax sheet) | E11: ='Tax - Canada (2026)'!D12/12 -> 3648.5275 | F11: ='Tax - Canada (2026)'!D12 -> 43782.33
D12: Provincial tax (from tax sheet) | E12: ='Tax - Canada (2026)'!I14/12 -> 1792.6721 | F12: ='Tax - Canada (2026)'!I14 -> 21512.066
D13: Monthly take-home pay | E13: =E10-E11-E12 -> 12308.8 | F13: =ROUND((F10-F11-F12)/12,0) -> 12309

Sheet Tax - Canada (2026)
A1: Federal + BC income tax (2026)
A2: Marginal brackets, computed from annual taxable income. Brackets and basic amounts are editable yellow cells. Links in References below.
D3: Taxable income ($) (= annual net) | E3: ='Rule of 60'!F10 -> 213000
A4: Lower ($) | B4: Upper ($) | C4: Rate | D4: Tax in bracket | F4: Lower ($) | G4: Upper ($) | H4: Rate | I4: Tax in bracket
A5: 0 | B5: 58523 | C5: 0.14 | D5: =MAX(0,MIN($E$3,B5)-A5)*C5 -> 8193.22 | F5: 0 | G5: 50363 | H5: 0.0506 | I5: =MAX(0,MIN($E$3,G5)-F5)*H5 -> 2548.3678
A6: 58523 | B6: 117045 | C6: 0.205 | D6: =MAX(0,MIN($E$3,B6)-A6)*C6 -> 11997.01 | F6: 50363 | G6: 100728 | H6: 0.077 | I6: =MAX(0,MIN($E$3,G6)-F6)*H6 -> 3878.105
A7: 117045 | B7: 181440 | C7: 0.26 | D7: =MAX(0,MIN($E$3,B7)-A7)*C7 -> 16742.7 | F7: 100728 | G7: 115648 | H7: 0.105 | I7: =MAX(0,MIN($E$3,G7)-F7)*H7 -> 1566.6
A8: 181440 | B8: 258482 | C8: 0.29 | D8: =MAX(0,MIN($E$3,B8)-A8)*C8 -> 9152.4 | F8: 115648 | G8: 140430 | H8: 0.1229 | I8: =MAX(0,MIN($E$3,G8)-F8)*H8 -> 3045.7078
A9: 258482 | B9: 3000000000 | C9: 0.33 | D9: =MAX(0,MIN($E$3,B9)-A9)*C9 -> 0 | F9: 140430 | G9: 190405 | H9: 0.147 | I9: =MAX(0,MIN($E$3,G9)-F9)*H9 -> 7346.325
A10: Federal tax (before credits) | D10: =SUM(D5:D9) -> 46085.33 | F10: 190405 | G10: 265545 | H10: 0.168 | I10: =MAX(0,MIN($E$3,G10)-F10)*H10 -> 3795.96
A11: Less federal basic amount credit | B11: 16452 | D11: =-ROUND(B11*C5,0) -> -2303 | F11: 265545 | G11: 3000000000 | H11: 0.205 | I11: =MAX(0,MIN($E$3,G11)-F11)*H11 -> 0
A12: Federal tax payable | D12: =D10+D11 -> 43782.33 | F12: BC tax (before credits) | I12: =SUM(I5:I11) -> 22181.066
A13: Federal effective rate | D13: =D12/$E$3 -> 0.20555085 | F13: Less BC basic amount credit | G13: 13216 | I13: =-ROUND(G13*H5,0) -> -669
F14: BC tax payable | I14: =I12+I13 -> 21512.066
F15: BC effective rate | I15: =I14/$E$3 -> 0.10099561
D17: Combined federal + BC tax | E17: =D12+I14 -> 65294.396 | F17: Combined effective rate | G17: =(D12+I14)/$E$3 -> 0.30654646
A19: References
A20: Canada.ca 2026 federal rates & brackets
A21: gov.bc.ca BC personal income tax rates
A22: TaxTips.ca BC 2026 & 2025 rates / basic amounts
A23: WOWA.ca BC income tax calculator & brackets
A25: Note: BC's 2026 Budget proposed raising the lowest provincial bracket from 5.06% to 5.6%. CPP is not included here; self-employed pay both halves.
